flickrsyncr/__init__.py
flickrsyncr/__main__.py
flickrsyncr/config.py
flickrsyncr/flickrwrapper.py
flickrsyncr/general.py
flickrsyncr/settings.py
flickrsyncr/status.py
flickrsyncr/sync.py
flickrsyncr/syncer.py
flickrsyncr-0.2.1.dist-info/LICENSE
flickrsyncr-0.2.1.dist-info/METADATA
flickrsyncr-0.2.1.dist-info/WHEEL
flickrsyncr-0.2.1.dist-info/entry_points.txt
flickrsyncr-0.2.1.dist-info/top_level.txt
flickrsyncr-0.2.1.dist-info/RECORD
