Metadata-Version: 2.1
Name: flickrsyncr
Version: 0.2.1
Summary: Syncs photos between local filesystem and Flickr album
Home-page: https://github.com/B-Con/flickrsyncr
Author: Brad Conte
Author-email: brad@bradconte.com
License: MIT License
Requires-Dist: configparser
Requires-Dist: flickrapi (==2.3.1)
Requires-Dist: setuptools
Requires-Dist: python-magic
